storedsecrets/__init__.py
storedsecrets-0.1.3.dist-info/METADATA
storedsecrets-0.1.3.dist-info/WHEEL
storedsecrets-0.1.3.dist-info/top_level.txt
storedsecrets-0.1.3.dist-info/RECORD
