Metadata-Version: 2.1
Name: storedsecrets
Version: 0.1.3
Summary: A module to handle secrets outside of projects
Home-page: https://gitlab.com/bth0mas/storedsecrets/tree/master/python_module
Author: Benjamin THOMAS
Author-email: bth0mas@free.fr
License: UNKNOWN
Platform: UNKNOWN
Classifier: Programming Language :: Python :: 3
Classifier: License :: OSI Approved :: MIT License
Classifier: Operating System :: OS Independent
Requires-Python: >=3.6
